Metadata-Version: 2.4
Name: x_4357_make_slack_dump_and_reset_x
Version: 0.20.17
Summary: Slack purge runner that archives channels into Change Control and optionally deletes the source history once evidence is captured.
Author-email: "RRGM (Software Tech Lead, Primus Pilus Night Watch AI Corp.)" <foo@bar.com>
Requires-Python: >=3.8
Requires-Dist: requests>=2.31.0
